xarray_dataclasses/__init__.py
xarray_dataclasses/dataarray.py
xarray_dataclasses/datamodel.py
xarray_dataclasses/dataoptions.py
xarray_dataclasses/dataset.py
xarray_dataclasses/py.typed
xarray_dataclasses/typing.py
xarray_dataclasses-1.9.0.dist-info/LICENSE
xarray_dataclasses-1.9.0.dist-info/METADATA
xarray_dataclasses-1.9.0.dist-info/WHEEL
xarray_dataclasses-1.9.0.dist-info/RECORD
