Metadata-Version: 2.1
Name: xarray-dataclasses
Version: 1.9.0
Summary: xarray data creation by data classes
Home-page: https://github.com/astropenguin/xarray-dataclasses/
License: MIT
Keywords: xarray,dataclass,dataarray,dataset,typing
Author: Akio Taniguchi
Author-email: taniguchi@a.phys.nagoya-u.ac.jp
Requires-Python: >=3.8,<3.14
Classifier: License :: OSI Approved :: MIT License
Classifier: Programming Language :: Python :: 3
Classifier: Programming Language :: Python :: 3.8
Classifier: Programming Language :: Python :: 3.9
Classifier: Programming Language :: Python :: 3.10
Classifier: Programming Language :: Python :: 3.11
Classifier: Programming Language :: Python :: 3.12
Classifier: Programming Language :: Python :: 3.13
Requires-Dist: numpy (>=1.22) ; python_version >= "3.9" and python_version < "3.14"
Requires-Dist: numpy (>=1.22,<1.25) ; python_version >= "3.8" and python_version < "3.9"
Requires-Dist: typing-extensions (>=4.0,<5.0)
Requires-Dist: xarray (>=2022.3,<2023.2) ; python_version >= "3.8" and python_version < "3.9"
Requires-Dist: xarray (>=2022.3,<2025.0) ; python_version >= "3.9" and python_version < "3.14"
Project-URL: Documentation, https://astropenguin.github.io/xarray-dataclasses/
Project-URL: Repository, https://github.com/astropenguin/xarray-dataclasses/
